logiled/__init__.py
logiled/dll_definition.py
logiled/logi_led.py
logiled/dll/LogitechLedEnginesWrapper.dll
logiled-2023.11.12.1.dist-info/LICENSE.txt
logiled-2023.11.12.1.dist-info/METADATA
logiled-2023.11.12.1.dist-info/WHEEL
logiled-2023.11.12.1.dist-info/top_level.txt
logiled-2023.11.12.1.dist-info/RECORD
